easyrip/__init__.py
easyrip/__main__.py
easyrip/easyrip_command.py
easyrip/easyrip_log.py
easyrip/easyrip_main.py
easyrip/easyrip_prompt.py
easyrip/global_val.py
easyrip/utils.py
easyrip/easyrip_config/config.py
easyrip/easyrip_config/config_key.py
easyrip/easyrip_mlang/__init__.py
easyrip/easyrip_mlang/global_lang_val.py
easyrip/easyrip_mlang/lang_en.py
easyrip/easyrip_mlang/lang_tag_val.py
easyrip/easyrip_mlang/lang_zh_Hans_CN.py
easyrip/easyrip_mlang/translator.py
easyrip/easyrip_web/__init__.py
easyrip/easyrip_web/http_server.py
easyrip/easyrip_web/third_party_api.py
easyrip/ripper/media_info.py
easyrip/ripper/param.py
easyrip/ripper/ripper.py
easyrip/ripper/sub_and_font/__init__.py
easyrip/ripper/sub_and_font/ass.py
easyrip/ripper/sub_and_font/font.py
easyrip/ripper/sub_and_font/subset.py
easyrip-4.15.3.dist-info/licenses/LICENSE
easyrip-4.15.3.dist-info/METADATA
easyrip-4.15.3.dist-info/WHEEL
easyrip-4.15.3.dist-info/entry_points.txt
easyrip-4.15.3.dist-info/top_level.txt
easyrip-4.15.3.dist-info/RECORD
