Metadata-Version: 2.4
Name: easyrip
Version: 4.15.3
Author: op200
License-Expression: AGPL-3.0-or-later
Project-URL: Homepage, https://github.com/op200/EasyRip
Project-URL: Source, https://github.com/op200/EasyRip
Classifier: Topic :: Multimedia
Classifier: Development Status :: 5 - Production/Stable
Classifier: Programming Language :: Python :: 3.12
Classifier: Programming Language :: Python :: 3.13
Classifier: Programming Language :: Python :: 3.14
Classifier: Operating System :: Microsoft :: Windows :: Windows 10
Classifier: Operating System :: Microsoft :: Windows :: Windows 11
Classifier: Environment :: Console
Classifier: Intended Audience :: Developers
Classifier: Intended Audience :: End Users/Desktop
Classifier: Intended Audience :: Information Technology
Classifier: Typing :: Typed
Requires-Python: >=3.12
License-File: LICENSE
Requires-Dist: pyperclip>=1.11.0
Requires-Dist: prompt-toolkit>=3.0.52
Requires-Dist: fonttools>=4.61.1
Requires-Dist: pycryptodome>=3.23.0
Dynamic: license-file
